rusty_zip-0.1.0a2.dist-info/METADATA
rusty_zip-0.1.0a2.dist-info/WHEEL
rusty_zip-0.1.0a2.dist-info/licenses/LICENSE
rusty_zip/__init__.py
rusty_zip/_rust.cp310-win_amd64.pyd
rusty_zip-0.1.0a2.dist-info/RECORD
