Metadata-Version: 2.4
Name: rusty-zip
Version: 0.1.0a2
Classifier: Development Status :: 3 - Alpha
Classifier: Intended Audience :: Developers
Classifier: License :: OSI Approved :: MIT License
Classifier: Programming Language :: Rust
Classifier: Programming Language :: Python :: Implementation :: CPython
Classifier: Programming Language :: Python :: Implementation :: PyPy
Classifier: Programming Language :: Python :: 3.9
Classifier: Programming Language :: Python :: 3.10
Classifier: Programming Language :: Python :: 3.11
Classifier: Programming Language :: Python :: 3.12
Classifier: Topic :: System :: Archiving :: Compression
Requires-Dist: maturin>=1.8.3
License-File: LICENSE
Summary: Python wrapper for Rust's zip crate with legacy ZipCrypto encryption support
Keywords: zip,compression,zipcrypto,rust
Author: Hao Guan <gh@raptium.net>
Author-email: Hao Guan <gh@raptium.net>
Maintainer-email: Hao Guan <gh@raptium.net>
License: MIT
Requires-Python: >=3.9
Project-URL: Source Code, https://github.com/raptium/rusty-zip
